tx_engine-0.7.5.dist-info/METADATA
tx_engine-0.7.5.dist-info/WHEEL
tx_engine-0.7.5.dist-info/licenses/LICENSE
tx_engine-0.7.5.dist-info/licenses/LICENSE-rust-sv
tx_engine/__init__.py
tx_engine/engine/__init__.py
tx_engine/engine/context.py
tx_engine/engine/cryptography_utils.py
tx_engine/engine/engine_types.py
tx_engine/engine/op_code_names.py
tx_engine/engine/op_codes.py
tx_engine/engine/util.py
tx_engine/interface/__init__.py
tx_engine/interface/blockchain_interface.py
tx_engine/interface/interface_factory.py
tx_engine/interface/mock_interface.py
tx_engine/interface/rpc_interface.py
tx_engine/interface/verify_script.py
tx_engine/interface/woc.py
tx_engine/interface/woc_interface.py
tx_engine/tx/__init__.py
tx_engine/tx/sighash.py
tx_engine/tx_engine.cp314-win_amd64.pyd
tx_engine-0.7.5.dist-info/RECORD
