Metadata-Version: 2.4
Name: tx_engine
Version: 0.7.5
Classifier: Programming Language :: Rust
Classifier: Programming Language :: Python :: Implementation :: CPython
Classifier: Programming Language :: Python :: Implementation :: PyPy
Requires-Dist: requests==2.32.5
Requires-Dist: python-bitcoinrpc==1.0
Requires-Dist: cryptography==46.0.3
License-File: LICENSE
License-File: LICENSE-rust-sv
Summary: This library provides a Python interface for building BitcoinSV scripts and transactions.
Requires-Python: >=3.11
